ciliaseg/__init__.py
ciliaseg/__main__.py
ciliaseg/app.py
ciliaseg/main.py
ciliaseg/eval/__init__.py
ciliaseg/eval/model.py
ciliaseg/eval/polygon.py
ciliaseg/gui/__init__.py
ciliaseg/gui/canvas.py
ciliaseg/state/__init__.py
ciliaseg/state/image.py
ciliaseg/state/stereocilia.py
ciliaseg/train/__init__.py
ciliaseg/utils/__init__.py
ciliaseg/utils/io.py
ciliaseg/widgets/__init__.py
ciliaseg/widgets/control.py
ciliaseg-0.0.6.dev20240417.dist-info/METADATA
ciliaseg-0.0.6.dev20240417.dist-info/WHEEL
ciliaseg-0.0.6.dev20240417.dist-info/entry_points.txt
ciliaseg-0.0.6.dev20240417.dist-info/top_level.txt
ciliaseg-0.0.6.dev20240417.dist-info/RECORD
